resonant_settings/__init__.py
resonant_settings/_env.py
resonant_settings/allauth.py
resonant_settings/celery.py
resonant_settings/django.py
resonant_settings/django_extensions.py
resonant_settings/logging.py
resonant_settings/oauth_toolkit.py
resonant_settings/py.typed
resonant_settings/rest_framework.py
resonant_settings/allauth_support/__init__.py
resonant_settings/allauth_support/adapter.py
resonant_settings/allauth_support/apps.py
resonant_settings/allauth_support/createsuperuser.py
resonant_settings/allauth_support/receiver.py
resonant_settings/allauth_support/utils.py
resonant_settings/allauth_support/management/commands/createsuperuser.py
resonant_settings/development/__init__.py
resonant_settings/development/celery.py
resonant_settings/development/debug_toolbar.py
resonant_settings/development/minio_storage.py
resonant_settings/production/__init__.py
resonant_settings/production/email.py
resonant_settings/production/https.py
resonant_settings/production/s3_storage.py
django_resonant_settings-0.44.0.dist-info/METADATA
django_resonant_settings-0.44.0.dist-info/WHEEL
django_resonant_settings-0.44.0.dist-info/licenses/LICENSE
django_resonant_settings-0.44.0.dist-info/licenses/NOTICE
django_resonant_settings-0.44.0.dist-info/RECORD
