Metadata-Version: 2.4
Name: django-resonant-settings
Version: 0.44.0
Summary: Shared Django settings for Resonant applications.
Project-URL: Repository, https://github.com/kitware-resonant/cookiecutter-resonant
Project-URL: Bug Reports, https://github.com/kitware-resonant/cookiecutter-resonant/issues
Maintainer-email: "Kitware, Inc." <kitware@kitware.com>
License-Expression: Apache-2.0
License-File: LICENSE
License-File: NOTICE
Keywords: django,resonant,setting,settings
Classifier: Development Status :: 3 - Alpha
Classifier: Environment :: Web Environment
Classifier: Framework :: Django
Classifier: Framework :: Django :: 5
Classifier: Framework :: Django :: 5.1
Classifier: Framework :: Django :: 5.2
Classifier: Intended Audience :: Developers
Classifier: Operating System :: OS Independent
Classifier: Programming Language :: Python
Classifier: Programming Language :: Python :: 3
Classifier: Programming Language :: Python :: 3.10
Classifier: Programming Language :: Python :: 3.11
Classifier: Programming Language :: Python :: 3.12
Classifier: Programming Language :: Python :: 3.13
Classifier: Programming Language :: Python :: 3.14
Requires-Python: >=3.10
Requires-Dist: django-environ
Provides-Extra: allauth
Requires-Dist: django-allauth; extra == 'allauth'
Provides-Extra: celery
Requires-Dist: celery; extra == 'celery'
